pandora/__init__.py
pandora/__main__.py
pandora/cloud_launcher.py
pandora/launcher.py
pandora/py.typed
pandora/bots/__init__.py
pandora/bots/legacy.py
pandora/bots/server.py
pandora/exts/__init__.py
pandora/exts/config.py
pandora/exts/hooks.py
pandora/exts/token.py
pandora/flask/static/apple-touch-icon.png
pandora/flask/static/favicon-16x16.png
pandora/flask/static/favicon-32x32.png
pandora/flask/static/_next/static/chunks/113-23682f80a24dd00d.js
pandora/flask/static/_next/static/chunks/14-0cb0d20affbd720d.js
pandora/flask/static/_next/static/chunks/174-bd28069f281ef76f.js
pandora/flask/static/_next/static/chunks/1f110208-44a6f43ddc5e9011.js
pandora/flask/static/_next/static/chunks/264-13e92c51b0315184.js
pandora/flask/static/_next/static/chunks/360-442b869f1ba4bb1b.js
pandora/flask/static/_next/static/chunks/424-d1d3bfe6a3ca6c4a.js
pandora/flask/static/_next/static/chunks/554.9b8bfd0762461d74.js
pandora/flask/static/_next/static/chunks/68a27ff6-1185184b61bc22d0.js
pandora/flask/static/_next/static/chunks/762-222df1028c0c1555.js
pandora/flask/static/_next/static/chunks/949.1a6eb804b5e91f61.js
pandora/flask/static/_next/static/chunks/bd26816a-981e1ddc27b37cc6.js
pandora/flask/static/_next/static/chunks/framework-7a789ee31d2a7534.js
pandora/flask/static/_next/static/chunks/main-149b337e061b4d04.js
pandora/flask/static/_next/static/chunks/polyfills-c67a75d1b6f99dc8.js
pandora/flask/static/_next/static/chunks/webpack-c9a868e8e0796ec6.js
pandora/flask/static/_next/static/chunks/pages/_app-aaa11de1926dcafe.js
pandora/flask/static/_next/static/chunks/pages/_error-786d27d84962122a.js
pandora/flask/static/_next/static/chunks/pages/chat/[[...chatId]]-76751174916fa3f8.js
pandora/flask/static/_next/static/css/ac221fb2caad35a6.css
pandora/flask/static/_next/static/olf4sv64FWIcQ_zCGl90t/_buildManifest.js
pandora/flask/static/_next/static/olf4sv64FWIcQ_zCGl90t/_ssgManifest.js
pandora/flask/static/fonts/KaTeX_Caligraphic-Bold.woff
Pandora_ChatGPT-1.3.5.dist-info/LICENSE
Pandora_ChatGPT-1.3.5.dist-info/METADATA
Pandora_ChatGPT-1.3.5.dist-info/WHEEL
Pandora_ChatGPT-1.3.5.dist-info/entry_points.txt
Pandora_ChatGPT-1.3.5.dist-info/top_level.txt
Pandora_ChatGPT-1.3.5.dist-info/RECORD
